mojangson/GRAMMAR.lark
mojangson/__init__.py
mojangson/__main__.py
mojangson/cli.py
mojangson/mojangson.py
mojangson/transformer.py
mojangson-0.2.1.dist-info/licenses/LICENSE
mojangson-0.2.1.dist-info/METADATA
mojangson-0.2.1.dist-info/WHEEL
mojangson-0.2.1.dist-info/entry_points.txt
mojangson-0.2.1.dist-info/top_level.txt
mojangson-0.2.1.dist-info/RECORD
