Metadata-Version: 2.4
Name: mojangson
Version: 0.2.1
Summary: Python Mojangson parser
Home-page: https://github.com/MushroomForYou/mojangson
Author: mushroomforyou
Author-email: mushroomforus@gmail.com
Project-URL: GitHub, https://github.com/MushroomForYou/mojangson
Keywords: json mojang nbt parser
Classifier: Programming Language :: Python :: 3.10
Classifier: Programming Language :: Python :: 3.11
Classifier: Programming Language :: Python :: 3.12
Classifier: Programming Language :: Python :: 3.13
Classifier: License :: OSI Approved :: MIT License
Classifier: Operating System :: OS Independent
Requires-Python: >=3.10
License-File: LICENSE
Requires-Dist: lark>=1.2.2
Dynamic: author
Dynamic: author-email
Dynamic: classifier
Dynamic: description
Dynamic: description-content-type
Dynamic: home-page
Dynamic: keywords
Dynamic: license-file
Dynamic: project-url
Dynamic: requires-dist
Dynamic: requires-python
Dynamic: summary
